textstat_cli_tddschn/__init__.py
textstat_cli_tddschn/cli.py
textstat_cli_tddschn-0.1.1.dist-info/METADATA
textstat_cli_tddschn-0.1.1.dist-info/WHEEL
textstat_cli_tddschn-0.1.1.dist-info/entry_points.txt
textstat_cli_tddschn-0.1.1.dist-info/RECORD
