Metadata-Version: 2.1
Name: textstat-cli-tddschn
Version: 0.1.1
Summary: 
Home-page: https://github.com/tddschn/textstat-cli-tddschn
License: MIT
Keywords: text,text-analysis,cli,textstat,utility,command-line
Author: Teddy Xinyuan Chen
Author-email: 45612704+tddschn@users.noreply.github.com
Requires-Python: >=3.10,<3.12
Classifier: License :: OSI Approved :: MIT License
Classifier: Programming Language :: Python :: 3
Classifier: Programming Language :: Python :: 3.10
Classifier: Programming Language :: Python :: 3.11
Classifier: Topic :: Utilities
Requires-Dist: tabulate (>=0.9.0,<0.10.0)
Requires-Dist: textstat (>=0.7.3,<0.8.0)
Project-URL: Bug Tracker, https://github.com/tddschn/textstat-cli-tddschn/issues
Project-URL: Repository, https://github.com/tddschn/textstat-cli-tddschn
